{
  "id": "NSP13:T:115:A",
  "display_name": "T115A",
  "variation.featureLoc.feature.name": "NSP13",
  "codon_label": "115",
  "codon_label_int": 115,
  "reference_aa": "T",
  "reference_nt": 16579,
  "replacement_aa": "A",
  "radical_hanada_category_i": false,
  "radical_hanada_category_ii": false,
  "radical_hanada_category_iii": true,
  "grantham_distance_double": 58.02332760382417,
  "grantham_distance_int": 58,
  "miyata_distance": 0.9021839838528766,
  "parent_feature": "ORF_1ab",
  "parent_codon_label": "5439"
}