{
  "id": "NSP15:A:283:V",
  "display_name": "A283V",
  "variation.featureLoc.feature.name": "NSP15",
  "codon_label": "283",
  "codon_label_int": 283,
  "reference_aa": "A",
  "reference_nt": 20467,
  "replacement_aa": "V",
  "radical_hanada_category_i": true,
  "radical_hanada_category_ii": false,
  "radical_hanada_category_iii": false,
  "grantham_distance_double": 64.43025059480746,
  "grantham_distance_int": 64,
  "miyata_distance": 1.847329414521172,
  "parent_feature": "ORF_1ab",
  "parent_codon_label": "6735"
}