{
  "id": "NSP2:T:616:P",
  "display_name": "T616P",
  "variation.featureLoc.feature.name": "NSP2",
  "codon_label": "616",
  "codon_label_int": 616,
  "reference_aa": "T",
  "reference_nt": 2651,
  "replacement_aa": "P",
  "radical_hanada_category_i": false,
  "radical_hanada_category_ii": false,
  "radical_hanada_category_iii": true,
  "grantham_distance_double": 37.56362475504698,
  "grantham_distance_int": 38,
  "miyata_distance": 0.873755109177339,
  "parent_feature": "ORF_1a",
  "parent_codon_label": "796"
}