{
  "id": "NSP3:Y:1185:N",
  "display_name": "Y1185N",
  "variation.featureLoc.feature.name": "NSP3",
  "codon_label": "1185",
  "codon_label_int": 1185,
  "reference_aa": "Y",
  "reference_nt": 6272,
  "replacement_aa": "N",
  "radical_hanada_category_i": true,
  "radical_hanada_category_ii": true,
  "radical_hanada_category_iii": false,
  "grantham_distance_double": 142.22936956562143,
  "grantham_distance_int": 142,
  "miyata_distance": 3.416303226515753,
  "parent_feature": "ORF_1a",
  "parent_codon_label": "2003"
}