{
  "id": "NSP3:S:769:P",
  "display_name": "S769P",
  "variation.featureLoc.feature.name": "NSP3",
  "codon_label": "769",
  "codon_label_int": 769,
  "reference_aa": "S",
  "reference_nt": 5024,
  "replacement_aa": "P",
  "radical_hanada_category_i": false,
  "radical_hanada_category_ii": false,
  "radical_hanada_category_iii": true,
  "grantham_distance_double": 73.35256887257073,
  "grantham_distance_int": 73,
  "miyata_distance": 0.5564160035374529,
  "parent_feature": "ORF_1a",
  "parent_codon_label": "1587"
}