{
  "id": "NSP4:C:88:G",
  "display_name": "C88G",
  "variation.featureLoc.feature.name": "NSP4",
  "codon_label": "88",
  "codon_label_int": 88,
  "reference_aa": "C",
  "reference_nt": 8816,
  "replacement_aa": "G",
  "radical_hanada_category_i": true,
  "radical_hanada_category_ii": false,
  "radical_hanada_category_iii": true,
  "grantham_distance_double": 158.2317728686345,
  "grantham_distance_int": 158,
  "miyata_distance": 2.2172032627151887,
  "parent_feature": "ORF_1a",
  "parent_codon_label": "2851"
}